<PolymerNanocomposite>
    <ID>L129_S11_Wu_2011</ID>
    <Control_ID>L129_S1_Wu_2011</Control_ID>
    <SchemaVersion>PNC_schema_041220</SchemaVersion>
    <DatasetID>5e9701a2c9db0157d0737e52</DatasetID>
    <SchemaID>5e96dbe7c49dc53363c20305</SchemaID>
    <DATA_SOURCE>
        <Citation>
            <CommonFields>
                <CitationType>research article</CitationType>
                <Publication>Journal of Materials Chemistry</Publication>
                <Title>Morphology-controllable graphene-TiO2 nanorod hybrid nanostructures for polymer composites with high dielectric performance</Title>
                <Author>Wu, Chao</Author>
                <Author>Huang, Xingyi</Author>
                <Author>Xie, Liyuan</Author>
                <Author>Wu, Xingfeng</Author>
                <Author>Yu, Jinghong</Author>
                <Author>Jiang, Pingkai</Author>
                <Publisher>The Royal Society of Chemistry</Publisher>
                <PublicationYear>2011</PublicationYear>
                <DOI>10.1039/c1jm12903a</DOI>
                <Volume>21</Volume>
                <URL>http://pubs.rsc.org/en/content/articlelanding/2011/jm/c1jm12903a</URL>
                <Language>English</Language>
                <Location>Department of Polymer Science and Engineering, Shanghai Key Lab of Electrical Insulation and Thermal Aging, Shanghai Jiao Tong University,Shanghai,China</Location>
                <DateOfCitation>2016-07-31</DateOfCitation>
            </CommonFields>
            <CitationType>
                <Journal>
                    <ISSN>1364-5501</ISSN>
                    <Issue>44</Issue>
                </Journal>
            </CitationType>
        </Citation>
    </DATA_SOURCE>
    <MATERIALS>
        <Matrix>
            <MatrixComponent>
                <ChemicalName>polystyrene</ChemicalName>
                <StdChemicalName>Polystyrene</StdChemicalName>
                <uSMILES> C(C(C1=CC=CC=C1)[*])[*] </uSMILES>
                <Abbreviation>PS</Abbreviation>
                <ManufacturerOrSourceName>Dow Chemistry</ManufacturerOrSourceName>
                <TradeName>STYRON666H</TradeName>
                <Density>
                    <description>inserted from ChemProps, NanoMine</description>
                    <value>1.04</value>
                    <unit>g/cm3</unit>
                </Density>
            </MatrixComponent>
        </Matrix>
        <Filler>
            <FillerComponent>
                <ChemicalName>Graphene Oxide</ChemicalName>
                <StdChemicalName>Graphene oxide</StdChemicalName>
                <Abbreviation>GO</Abbreviation>
                <ManufacturerOrSourceName>Sinopharm Chemical Reagent co., Ltd</ManufacturerOrSourceName>
                <Density>
                    <description>inserted from ChemProps, NanoMine</description>
                    <value>1.91</value>
                    <unit>g/cm3</unit>
                </Density>
                <FillerComponentComposition>
                    <volume>0.333</volume>
                </FillerComponentComposition>
                <FillerComponentInComposite>
                    <volume>0.023976</volume>
                </FillerComponentInComposite>
                <ParticleSurfaceTreatment>
                    <ChemicalName>n-Octyltriethoxysilane</ChemicalName>
                    <Abbreviation>OTES</Abbreviation>
                </ParticleSurfaceTreatment>
            </FillerComponent>
            <FillerComponent>
                <ChemicalName>Titanium Dioxide</ChemicalName>
                <StdChemicalName>Titanium dioxide</StdChemicalName>
                <Abbreviation>TiO2</Abbreviation>
                <Density>
                    <description>inserted from ChemProps, NanoMine</description>
                    <value>4.23</value>
                    <unit>g/cm3</unit>
                </Density>
                <NonSphericalShape>
                    <Width>
                        <value>3</value>
                        <unit>nm</unit>
                    </Width>
                    <Length>
                        <value>30</value>
                        <unit>nm</unit>
                    </Length>
                    <Depth>
                        <value>3</value>
                        <unit>nm</unit>
                    </Depth>
                </NonSphericalShape>
                <FillerComponentComposition>
                    <volume>0.667</volume>
                </FillerComponentComposition>
                <FillerComponentInComposite>
                    <volume>0.048024</volume>
                </FillerComponentInComposite>
            </FillerComponent>
            <FillerComposition>
                <Fraction>
                    <mass>
                        <value>0.20504469778519546</value>
                        <source>computed by NanoMine</source>
                    </mass>
                    <volume>
                        <value>0.072</value>
                        <source>reported</source>
                    </volume>
                </Fraction>
            </FillerComposition>
        </Filler>
    </MATERIALS>
    <PROCESSING>
        <SolutionProcessing>
            <ChooseParameter>
                <Mixing>
                    <Description>Magnetic</Description>
                    <MixingMethod>stirring</MixingMethod>
                    <ChemicalUsed>
                        <description>GO, ethanol, OTES</description>
                    </ChemicalUsed>
                    <Time>
                        <value>8</value>
                        <unit>hours</unit>
                    </Time>
                    <Temperature>
                        <value>70</value>
                        <unit>Celsius</unit>
                    </Temperature>
                </Mixing>
            </ChooseParameter>
            <ChooseParameter>
                <Mixing>
                    <Description>Magnetic</Description>
                    <MixingMethod>stirring</MixingMethod>
                    <ChemicalUsed>
                        <description>modified graphene, oleic acid, tetrabutyl titanate, triethyl amine</description>
                    </ChemicalUsed>
                    <Time>
                        <value>15</value>
                        <unit>hours</unit>
                    </Time>
                    <Temperature>
                        <value>180</value>
                        <unit>Celsius</unit>
                    </Temperature>
                </Mixing>
            </ChooseParameter>
        </SolutionProcessing>
        <SolutionProcessing>
            <ChooseParameter>
                <Centrifugation>Used</Centrifugation>
            </ChooseParameter>
        </SolutionProcessing>
    </PROCESSING>
    <CHARACTERIZATION>
        <Transmission_Electron_Microscopy>
            <EquipmentUsed>JEM- 2010, JEOL</EquipmentUsed>
        </Transmission_Electron_Microscopy>
        <Scanning_Electron_Microscopy>
            <EquipmentUsed>JSM-7401F, JEOL</EquipmentUsed>
        </Scanning_Electron_Microscopy>
        <Dielectric_and_Impedance_Spectroscopy_Analysis>
            <Equipment>Agilent 4294 impedance analyzer</Equipment>
        </Dielectric_and_Impedance_Spectroscopy_Analysis>
        <XRay_Diffraction_and_Scattering>
            <Equipment>JEM- 2010, JEOL</Equipment>
        </XRay_Diffraction_and_Scattering>
        <Raman_Spectroscopy>
            <Equipment>LabRam HR800, Jobin Yvon</Equipment>
        </Raman_Spectroscopy>
    </CHARACTERIZATION>
    <PROPERTIES>
        <Electrical>
            <AC_DielectricDispersion>
                <DielectricDispersionDependence>
                    <FrequencyDependence>
                        <condition>
                            <temperature>
                                <value>25</value>
                                <unit>Celsius</unit>
                            </temperature>
                        </condition>
                    </FrequencyDependence>
                </DielectricDispersionDependence>
                <Dielectric_Loss_Permittivity>
                    <data>
                        <description>At Room Temperature</description>
                        <AxisLabel>
                            <xName>Frequency</xName>
                            <xUnit>Hz</xUnit>
                            <yName>Permittivity</yName>
                        </AxisLabel>
                        <data>
                            <headers>
                                <column id="0">Frequency (Hz)</column>
                                <column id="1">Permittivity</column>
                            </headers>
                            <rows>
                                <row id="0">
                                    <column id="0">98.74024813245542</column>
                                    <column id="1">686.8777248548796</column>
                                </row>
                                <row id="1">
                                    <column id="0">137.82384915790558</column>
                                    <column id="1">664.8061608495068</column>
                                </row>
                                <row id="2">
                                    <column id="0">181.02786413284312</column>
                                    <column id="1">664.8061608495068</column>
                                </row>
                                <row id="3">
                                    <column id="0">260.62341903100423</column>
                                    <column id="1">583.3879397552116</column>
                                </row>
                                <row id="4">
                                    <column id="0">363.7840036958537</column>
                                    <column id="1">564.6418314067566</column>
                                </row>
                                <row id="5">
                                    <column id="0">523.7350133150014</column>
                                    <column id="1">495.49064693244515</column>
                                </row>
                                <row id="6">
                                    <column id="0">708.9200146352603</column>
                                    <column id="1">511.94093601198443</column>
                                </row>
                                <row id="7">
                                    <column id="0">1020.4034770855627</column>
                                    <column id="1">464.15888336127773</column>
                                </row>
                                <row id="8">
                                    <column id="0">1423.99600839</column>
                                    <column id="1">464.15888336127773</column>
                                </row>
                                <row id="9">
                                    <column id="0">2111.809415803318</column>
                                    <column id="1">449.24398347143836</column>
                                </row>
                                <row id="10">
                                    <column id="0">2774.400109552902</column>
                                    <column id="1">434.8083467104509</column>
                                </row>
                                <row id="11">
                                    <column id="0">3756.194222175612</column>
                                    <column id="1">434.8083467104509</column>
                                </row>
                                <row id="12">
                                    <column id="0">5244.106696113344</column>
                                    <column id="1">407.3137564447351</column>
                                </row>
                                <row id="13">
                                    <column id="0">7321.414552491446</column>
                                    <column id="1">381.55775399500476</column>
                                </row>
                                <row id="14">
                                    <column id="0">10538.278948705996</column>
                                    <column id="1">345.9450271974589</column>
                                </row>
                                <row id="15">
                                    <column id="0">14712.726747236817</column>
                                    <column id="1">324.0696035787167</column>
                                </row>
                                <row id="16">
                                    <column id="0">19944.90751769972</column>
                                    <column id="1">266.398585726</column>
                                </row>
                                <row id="17">
                                    <column id="0">29604.058276931708</column>
                                    <column id="1">226.2611181825071</column>
                                </row>
                                <row id="18">
                                    <column id="0">38951.02138170805</column>
                                    <column id="1">174.2347400593542</column>
                                </row>
                                <row id="19">
                                    <column id="0">54473.95107746561</column>
                                    <column id="1">125.6871215154859</column>
                                </row>
                                <row id="20">
                                    <column id="0">78509.7291168</column>
                                    <column id="1">93.67661856684065</column>
                                </row>
                                <row id="21">
                                    <column id="0">109821.36147720541</column>
                                    <column id="1">65.40377817119526</column>
                                </row>
                                <row id="22">
                                    <column id="0">158312.3312866716</column>
                                    <column id="1">47.18010089018163</column>
                                </row>
                                <row id="23">
                                    <column id="0">208386.21235628813</column>
                                    <column id="1">34.034148825183074</column>
                                </row>
                                <row id="24">
                                    <column id="0">300268.8391841141</column>
                                    <column id="1">26.2083521965</column>
                                </row>
                                <row id="25">
                                    <column id="0">419392.2306049136</column>
                                    <column id="1">22.998638539612084</column>
                                </row>
                                <row id="26">
                                    <column id="0">604052.9755545541</column>
                                    <column id="1">18.905829836907586</column>
                                </row>
                                <row id="27">
                                    <column id="0">818340.2841626805</column>
                                    <column id="1">17.141252532913125</column>
                                </row>
                                <row id="28">
                                    <column id="0">1178153.6715959446</column>
                                    <column id="1">15.041978532842908</column>
                                </row>
                                <row id="29">
                                    <column id="0">1596788.8096485175</column>
                                    <column id="1">12.775649214671143</column>
                                </row>
                                <row id="30">
                                    <column id="0">2297887.983451619</column>
                                    <column id="1">11.967796184265058</column>
                                </row>
                                <row id="31">
                                    <column id="0">3113730.8891729317</column>
                                    <column id="1">10.502110796366658</column>
                                </row>
                                <row id="32">
                                    <column id="0">4348083.467104509</column>
                                    <column id="1">9.521895354084075</column>
                                </row>
                                <row id="33">
                                    <column id="0">6261223.422159975</column>
                                    <column id="1">8.087260238869234</column>
                                </row>
                                <row id="34">
                                    <column id="0">8748950.38592</column>
                                    <column id="1">6.648061608495068</column>
                                </row>
                            </rows>
                        </data>
                    </data>
                </Dielectric_Loss_Permittivity>
                <Dielectric_Loss_Tangent>
                    <data>
                        <description>At Room Temperature</description>
                        <AxisLabel>
                            <xName>Frequency</xName>
                            <xUnit>Hz</xUnit>
                            <yName>Loss Tangent</yName>
                        </AxisLabel>
                        <data>
                            <headers>
                                <column id="0">Frequency (Hz)</column>
                                <column id="1">Loss Tangent</column>
                            </headers>
                            <rows>
                                <row id="0">
                                    <column id="0">101.62969997467138</column>
                                    <column id="1">2.507802241488596</column>
                                </row>
                                <row id="1">
                                    <column id="0">133.48783705640048</column>
                                    <column id="1">2.507802241488596</column>
                                </row>
                                <row id="2">
                                    <column id="0">197.9644995427797</column>
                                    <column id="1">2.3883164656930287</column>
                                </row>
                                <row id="3">
                                    <column id="0">276.6190531238962</column>
                                    <column id="1">1.781900264199618</column>
                                </row>
                                <row id="4">
                                    <column id="0">374.9492380232333</column>
                                    <column id="1">1.362308976812705</column>
                                </row>
                                <row id="5">
                                    <column id="0">539.8656072732846</column>
                                    <column id="1">1.0936270860789263</column>
                                </row>
                                <row id="6">
                                    <column id="0">709.8582875463667</column>
                                    <column id="1">0.8567659353696422</column>
                                </row>
                                <row id="7">
                                    <column id="0">1053.6326786789025</column>
                                    <column id="1">0.6712049082852022</column>
                                </row>
                                <row id="8">
                                    <column id="0">1471.6279535031158</column>
                                    <column id="1">0.5521403293429307</column>
                                </row>
                                <row id="9">
                                    <column id="0">2055.0095133299933</column>
                                    <column id="1">0.47691966440525263</column>
                                </row>
                                <row id="10">
                                    <column id="0">2619.7688379447577</column>
                                    <column id="1">0.43255606206763086</column>
                                </row>
                                <row id="11">
                                    <column id="0">3768.809648688555</column>
                                    <column id="1">0.4221256050276529</column>
                                </row>
                                <row id="12">
                                    <column id="0">5421.243818133518</column>
                                    <column id="1">0.4221256050276529</column>
                                </row>
                                <row id="13">
                                    <column id="0">7794.848872673077</column>
                                    <column id="1">0.4654194439544711</column>
                                </row>
                                <row id="14">
                                    <column id="0">10873.229738424976</column>
                                    <column id="1">0.5131535643205029</column>
                                </row>
                                <row id="15">
                                    <column id="0">15625.533422079357</column>
                                    <column id="1">0.6392249387894234</column>
                                </row>
                                <row id="16">
                                    <column id="0">21796.447559020227</column>
                                    <column id="1">0.7047848129319582</column>
                                </row>
                                <row id="17">
                                    <column id="0">28604.529912349128</column>
                                    <column id="1">0.8567659353696422</column>
                                </row>
                                <row id="18">
                                    <column id="0">41106.5570139</column>
                                    <column id="1">1.0672558677804762</column>
                                </row>
                                <row id="19">
                                    <column id="0">57322.15176940118</column>
                                    <column id="1">1.2661160034971233</column>
                                </row>
                                <row id="20">
                                    <column id="0">82402.09540685154</column>
                                    <column id="1">1.4658101968369108</column>
                                </row>
                                <row id="21">
                                    <column id="0">111526.409305</column>
                                    <column id="1">1.5771749065164233</column>
                                </row>
                                <row id="22">
                                    <column id="0">150912.1462594504</column>
                                    <column id="1">1.781900264199618</column>
                                </row>
                                <row id="23">
                                    <column id="0">217056.321254</column>
                                    <column id="1">1.8259298940867754</column>
                                </row>
                                <row id="24">
                                    <column id="0">293961.7800369825</column>
                                    <column id="1">1.6970005332974571</column>
                                </row>
                                <row id="25">
                                    <column id="0">422985.1185802862</column>
                                    <column id="1">1.5771749065164233</column>
                                </row>
                                <row id="26">
                                    <column id="0">572853.4311677936</column>
                                    <column id="1">1.4658101968369108</column>
                                </row>
                                <row id="27">
                                    <column id="0">875870.7482731935</column>
                                    <column id="1">1.329458887532024</column>
                                </row>
                                <row id="28">
                                    <column id="0">1116817.3345387315</column>
                                    <column id="1">1.1483404721348514</column>
                                </row>
                                <row id="29">
                                    <column id="0">1607518.0162858614</column>
                                    <column id="1">0.9918966673658262</column>
                                </row>
                                <row id="30">
                                    <column id="0">2383973.7508487357</column>
                                    <column id="1">0.9446371423329055</column>
                                </row>
                                <row id="31">
                                    <column id="0">3327601.412550479</column>
                                    <column id="1">0.8996293263537813</column>
                                </row>
                                <row id="32">
                                    <column id="0">4370245.741429038</column>
                                    <column id="1">0.9218585987046569</column>
                                </row>
                                <row id="33">
                                    <column id="0">6285033.638943537</column>
                                    <column id="1">0.9679785293848137</column>
                                </row>
                                <row id="34">
                                    <column id="0">8769028.062913487</column>
                                    <column id="1">1.0164058074270628</column>
                                </row>
                            </rows>
                        </data>
                    </data>
                </Dielectric_Loss_Tangent>
            </AC_DielectricDispersion>
        </Electrical>
    </PROPERTIES>
    <MICROSTRUCTURE>
        <LengthUnit>nm</LengthUnit>
        <ImageFile>
            <File>http://localhost/nmr/blob?id=5acf8d5be74a1d06fd9bba53</File>
            <Description>TEM images of GT-hybrid sheets fabricated with different initial weight ratios of tetrabutyl titanate : GO: (a) 40 : 1,TiO2 nanorods: (a) 2.4 : 4.8</Description>
            <MicroscopyType>TEM</MicroscopyType>
        </ImageFile>
    </MICROSTRUCTURE>
</PolymerNanocomposite>