<PolymerNanocomposite>
    <ID>L164_S7_Li_2009</ID>
    <Control_ID>L164_S7_Li_2009</Control_ID>
    <SchemaVersion>PNC_schema_041220</SchemaVersion>
    <DatasetID>5e97046ac9db0157d0737e6b</DatasetID>
    <SchemaID>5e96dbe7c49dc53363c20305</SchemaID>
    <DATA_SOURCE>
        <Citation>
            <CommonFields>
                <CitationType>research article</CitationType>
                <Publication>Advanced Materials</Publication>
                <Title>Nanocomposites of Ferroelectric Polymers with TiO2 Nanoparticles Exhibiting Significantly Enhanced Electrical Energy Density</Title>
                <Author>Li, Junjun</Author>
                <Author>Seok, Sang Il</Author>
                <Author>Chu, Baojin</Author>
                <Author>Dogan, Fatih</Author>
                <Author>Zhang, Qiming</Author>
                <Author>Wang, Qing</Author>
                <Keyword>polymer composites</Keyword>
                <Keyword>nanoparticles</Keyword>
                <Keyword>polymeric materials</Keyword>
                <Keyword>nanocomposites</Keyword>
                <Keyword>flexible electronics</Keyword>
                <Publisher>WILEY&#8208;VCH Verlag</Publisher>
                <PublicationYear>2009</PublicationYear>
                <DOI>10.1002/adma.200801106</DOI>
                <Volume>21</Volume>
                <URL>http://onlinelibrary.wiley.com/doi/10.1002/adma.200801106/abstract</URL>
                <Language>English</Language>
                <Location>Department of Materials Science and Engineering The Pennsylvania State University University Park, Pennsylvania 16802, USA</Location>
            </CommonFields>
            <CitationType>
                <Journal>
                    <ISSN>1521-4095</ISSN>
                    <Issue>2</Issue>
                </Journal>
            </CitationType>
        </Citation>
    </DATA_SOURCE>
    <MATERIALS>
        <Matrix>
            <MatrixComponent>
                <ChemicalName>poly[chlorotrifluoroethylene-co-(vinylidene fluoride)]</ChemicalName>
                <StdChemicalName>Poly(vinylidene fluoride-co-chlorotrifluoroethylene)</StdChemicalName>
                <uSMILES>C(C(F)(F)[*])[*].FC(F)(C(F)(Cl)[*])[*]</uSMILES>
                <Abbreviation>P(VDF-CTFE)</Abbreviation>
                <Density>
                    <description>inserted from ChemProps, NanoMine</description>
                    <value>1.82</value>
                    <unit>g/cm3</unit>
                </Density>
            </MatrixComponent>
            <Description>synthesized via a copolymerization of vinylidene fluoride (VDF) and chlorotrifluoroethylene (CTFE) and a subsequent dechlorination reaction</Description>
        </Matrix>
    </MATERIALS>
    <PROCESSING>
        <SolutionProcessing>
            <ChooseParameter>
                <Mixing>
                    <Description>Thin films of the nanocomposites were fabricated by casting DMF solution of the TiO2 nanoparticles and P(VDF-CTFE) followed by drying at 120 &#176;C for 8 h in vacuo.</Description>
                    <ChemicalUsed>
                        <description>P(VDF-CTFE)</description>
                    </ChemicalUsed>
                    <ChemicalUsed>
                        <description>DMF solution</description>
                    </ChemicalUsed>
                </Mixing>
            </ChooseParameter>
            <ChooseParameter>
                <Molding>
                    <MoldingMode>casting</MoldingMode>
                </Molding>
            </ChooseParameter>
            <ChooseParameter>
                <Drying-Evaporation>
                    <Temperature>
                        <value>120</value>
                        <unit>Celsius</unit>
                    </Temperature>
                    <Time>
                        <value>8</value>
                        <unit>hours</unit>
                    </Time>
                </Drying-Evaporation>
            </ChooseParameter>
            <ChooseParameter>
                <Molding>
                    <MoldingMode>hot-pressing</MoldingMode>
                    <MoldingInfo>
                        <Description>The film was further melt-pressed at 160 &#176;C under 3000 psi to remove voids and residual solvent.</Description>
                        <Temperature>
                            <value>160</value>
                            <unit>Celsius</unit>
                        </Temperature>
                        <Pressure>
                            <value>20.68427</value>
                            <unit>MPa</unit>
                        </Pressure>
                    </MoldingInfo>
                </Molding>
            </ChooseParameter>
        </SolutionProcessing>
    </PROCESSING>
    <PROPERTIES>
        <Electrical>
            <AC_DielectricDispersion>
                <Dielectric_Real_Permittivity>
                    <description>measured at 1 kHz and room temperature with a 1 V bias</description>
                    <value>12.2699386503</value>
                </Dielectric_Real_Permittivity>
            </AC_DielectricDispersion>
            <AC_DielectricDispersion>
                <Dielectric_Loss_Tangent>
                    <description>measured at 1 kHz and room temperature with a 1 V bias</description>
                    <value>0.0386977886978</value>
                </Dielectric_Loss_Tangent>
            </AC_DielectricDispersion>
        </Electrical>
    </PROPERTIES>
</PolymerNanocomposite>