<PolymerNanocomposite>
    <ID>L154_S5_Eitan_2005</ID>
    <Control_ID>L154_S1_Eitan_2005</Control_ID>
    <SchemaVersion>PNC_schema_041220</SchemaVersion>
    <DatasetID>5e9703e0c9db0157d0737e64</DatasetID>
    <SchemaID>5e96dbe7c49dc53363c20305</SchemaID>
    <DATA_SOURCE>
        <Citation>
            <CommonFields>
                <CitationType>research article</CitationType>
                <Publication>Composites Science and Technology</Publication>
                <Title>Reinforcement mechanisms in MWCNT-filled polycarbonate</Title>
                <Author>Eitan, A.</Author>
                <Author>Fisher, F.T.</Author>
                <Author>Andrews, R.</Author>
                <Author>Brinson, L.C.</Author>
                <Author>Schadler, L.S.</Author>
                <Keyword>Nanostructures</Keyword>
                <Keyword>Particle-reinforced composites</Keyword>
                <Keyword>Polymer&#8211;matrix composites</Keyword>
                <Keyword>Mechanical properties</Keyword>
                <Keyword>Complex moduli</Keyword>
                <Publisher>Elsevier</Publisher>
                <PublicationYear>2006</PublicationYear>
                <DOI>10.1016/j.compscitech.2005.10.004</DOI>
                <Volume>66</Volume>
                <URL>https://www.sciencedirect.com/science/article/pii/S0266353805003623?via%3Dihub</URL>
                <Language>English</Language>
                <Location>Materials Science and Engineering, Rensselaer Polytechnic Institute, Troy, NY 12180, USA</Location>
            </CommonFields>
            <CitationType>
                <Journal>
                    <ISSN>0266-3538</ISSN>
                    <Issue>9</Issue>
                </Journal>
            </CitationType>
        </Citation>
    </DATA_SOURCE>
    <MATERIALS>
        <Matrix>
            <MatrixComponent>
                <ChemicalName>poly(bisphenol A carbonate)</ChemicalName>
                <StdChemicalName>Poly(bisphenol A carbonate)</StdChemicalName>
                <uSMILES>CC(C)(C1=CC=C(O[*])C=C1)C2=CC=C(OC(=O)[*])C=C2</uSMILES>
                <Abbreviation>PC</Abbreviation>
                <PlasticType>thermoplastic</PlasticType>
                <PolymerType>homopolymer</PolymerType>
                <ManufacturerOrSourceName>General Electric</ManufacturerOrSourceName>
                <TradeName>Lexan 121</TradeName>
                <Density>
                    <description>inserted from ChemProps, NanoMine</description>
                    <value>1.2</value>
                    <unit>g/cm3</unit>
                </Density>
            </MatrixComponent>
        </Matrix>
        <Filler>
            <FillerComponent>
                <ChemicalName>multi-walled carbon nanotubes</ChemicalName>
                <StdChemicalName>Multi-wall carbon nanotubes</StdChemicalName>
                <Abbreviation>MWCNT</Abbreviation>
                <Density>
                    <description>inserted from ChemProps, NanoMine</description>
                    <value>2.6</value>
                    <unit>g/cm3</unit>
                </Density>
                <FillerComponentInComposite>
                    <mass>0.02</mass>
                    <volume>0.009331259720062208</volume>
                </FillerComponentInComposite>
                <ParticleSurfaceTreatment>
                    <ChemicalName>epoxide</ChemicalName>
                </ParticleSurfaceTreatment>
            </FillerComponent>
            <FillerComposition>
                <Fraction>
                    <mass>
                        <value>0.02</value>
                        <source>reported</source>
                    </mass>
                    <volume>
                        <value>0.009331259720062208</value>
                        <source>computed by NanoMine</source>
                    </volume>
                </Fraction>
            </FillerComposition>
            <Description>produced by thermal chemical vapor deposition of xylene&#8211;ferrocene at 700 C in a quartz tube furnace</Description>
        </Filler>
    </MATERIALS>
    <PROCESSING>
        <SolutionProcessing>
            <ChooseParameter>
                <Mixing>
                    <Description>in a water ice bath</Description>
                    <Mixer>Fisher Scientific FS60</Mixer>
                    <MixingMethod>ultra-sonication</MixingMethod>
                    <ChemicalUsed>
                        <description>MWCNT</description>
                    </ChemicalUsed>
                    <ChemicalUsed>
                        <description>tetrahydrofuran</description>
                    </ChemicalUsed>
                    <Time>
                        <value>3</value>
                        <unit>hours</unit>
                    </Time>
                </Mixing>
            </ChooseParameter>
            <ChooseParameter>
                <Drying-Evaporation>
                    <Description>PC pellets were dried</Description>
                    <Temperature>
                        <value>125</value>
                        <unit>Celsius</unit>
                    </Temperature>
                    <Time>
                        <value>2</value>
                        <unit>hours</unit>
                    </Time>
                </Drying-Evaporation>
            </ChooseParameter>
            <ChooseParameter>
                <Mixing>
                    <MixingMethod>ultra-sonication</MixingMethod>
                    <ChemicalUsed>
                        <description>MWCNT dispersion</description>
                    </ChemicalUsed>
                    <ChemicalUsed>
                        <description>PC solution</description>
                    </ChemicalUsed>
                    <Time>
                        <value>1</value>
                        <unit>hours</unit>
                    </Time>
                </Mixing>
            </ChooseParameter>
            <ChooseParameter>
                <Additive>
                    <Description>precipitation of the composite material</Description>
                    <Additive>methanol</Additive>
                </Additive>
            </ChooseParameter>
            <ChooseParameter>
                <Drying-Evaporation>
                    <Description>the composite material was dried under vacuum</Description>
                    <Temperature>
                        <value>70</value>
                        <unit>Celsius</unit>
                    </Temperature>
                    <Time>
                        <value>16</value>
                        <unit>hours</unit>
                    </Time>
                </Drying-Evaporation>
            </ChooseParameter>
            <ChooseParameter>
                <Molding>
                    <MoldingMode>hot-pressing</MoldingMode>
                </Molding>
            </ChooseParameter>
        </SolutionProcessing>
    </PROCESSING>
    <CHARACTERIZATION>
        <Scanning_Electron_Microscopy>
            <Description>used</Description>
        </Scanning_Electron_Microscopy>
        <Dynamic_Mechanical_Analysis>
            <Equipment>Rheometrics DMTA-V</Equipment>
        </Dynamic_Mechanical_Analysis>
        <Raman_Spectroscopy>
            <Equipment>Reinshaw S2000</Equipment>
        </Raman_Spectroscopy>
    </CHARACTERIZATION>
    <PROPERTIES>
        <Mechanical>
            <Tensile>
                <TensileModulus>
                    <value>2.8</value>
                    <unit>GPa</unit>
                    <uncertainty>
                        <type>absolute</type>
                        <value>0.1</value>
                    </uncertainty>
                </TensileModulus>
                <TensileStressAtYield>
                    <value>69</value>
                    <unit>MPa</unit>
                </TensileStressAtYield>
                <ElongationAtYield>
                    <value>5.0</value>
                    <unit>%</unit>
                    <uncertainty>
                        <type>absolute</type>
                        <value>0.2</value>
                    </uncertainty>
                </ElongationAtYield>
                <ElongationAtBreak>
                    <value>50</value>
                    <unit>%</unit>
                    <uncertainty>
                        <type>absolute</type>
                        <value>20</value>
                    </uncertainty>
                </ElongationAtBreak>
            </Tensile>
        </Mechanical>
    </PROPERTIES>
</PolymerNanocomposite>